{"id":"1010","taxa_kind_id":"15","name":"Sophora japonica","description":"Albero, generalm. coltiv. in forme a rami penduli; getti giovani grigio-plumbei. Fg. (15-25 cm), imparipennate a 7-13 segm. lanceolati (1-2.5 X 4-6 cm), interi, acuti, ondulati, verde-glauchi di sotto, lucidi di sopra. Fi. in racemi formanti una pannocchia; corolla giallo-pallida 10-15 mm; legume formato da 2-7 logge ellissoidali (8-10 X 9-15 mm), generalm. divise fra loro da una strozzatura, dapprima verde-vetrose e ripiene di liquido giallo, alla fine brune e raggrinzite.<br \/><br \/>Inselvatichita in Romagna: R.; altrove comunem. coltiv.","creation_datetime":"2015-10-27 12:50:28","change_datetime":"2015-11-02 17:36:21","col_id":"55933fde1ef4b98b216ea29b55210988","eol_id":"702857","is_list":"0","taxa_kind_initials":"Sp.","taxa_kind_name":"Specie","status":"1","parent_taxa_id":"968","parent_taxa_name":"Leguminosae IV","parent_taxa_initials":"Gruppo","dico":{},"image":{"0":{"id":"526","taxa_id":"1010","filename":"\/00\/05\/26.png"}},"attribute":{"0":{"name":"Nome Italiano","value":"Sofora"},"1":{"name":"Portamento","value":"Albero"},"2":{"name":"Altezza","value":"3-10 m"},"3":{"name":"Tipo di vegetazione","value":"Pianta ornam. per parchi e giardini"},"4":{"name":"Limite altitudinale inferiore","value":"0"},"5":{"name":"Limite altitudinale superiore","value":"500"},"6":{"name":"Inizio fioritura","value":"Giugno"},"7":{"name":"Fine fioritura","value":"Luglio"},"8":{"name":"Autore","value":"Linneo"},"9":{"name":"Forma biologica","value":"P scap"},"10":{"name":"Codifica numerica","value":"3602001"},"11":{"name":"Progressivo","value":"1575\/XII"}},"region":{}}