{"id":"1057","taxa_kind_id":"15","name":"Genista holopetala","description":"Simile a {t1608}, ma minore; rami giovani, fg. e calice con pelosit\u00e0 sericea; segm. convoluti (1 x 12-22 mm), se spianati larghi fino a 2 mm; fi. all'asc. di brattee 3-fogliate; calice 5 mm; vessillo 10-11 mm con peli sericei.<br \/><br \/>N-Illir.<br \/>Endemismo N-iliirico ad areale frammentato (Velebit, Tarnova) sfiora il nostro confine orient. sul M. Caven pr. Gorizia (in terr. jugoslavo); l'unica stazione ital. pr. Trieste: RR.<br \/><br \/><strong>Nota<\/strong> - La stazione pi\u00f9 nota in terr. italiano (M. Spaccato pr. Trieste) distribuita anche nella FI. Ital. Exs. n. 865 \u00e8 estinta dal 1943 a causa di un incendio causato dai partigiani durante un'incursione verso la citt\u00e0: la sua zona \u00e8 ora rimboschita e le mutate condizioni ecologiche non permettono il reimpianto della specie, che tuttavia \u00e8 stata rinvenuta (Poldini, Pubbl. Ist. Bot. Univ. Trieste n. 19) a poca distanza, ancora in territorio italiano, in una localit\u00e0 che non viene qui nominata per motivi di conservazione naturalistica. Su {t1608} e {t1609} cfr. Mayer E., Glasnik R. Zav. Z. Prir. Muz. Titogr. 3: 37-47 (1970).","creation_datetime":"2015-11-06 12:05:22","change_datetime":"2015-11-13 11:44:55","col_id":"5d515de1d559acc3220a226e5bee617c","eol_id":"703760","is_list":"0","taxa_kind_initials":"Sp.","taxa_kind_name":"Specie","status":"1","parent_taxa_id":"1052","parent_taxa_name":"Genista I","parent_taxa_initials":"Gruppo","dico":{},"image":{},"attribute":{"0":{"name":"Nome Italiano","value":"Ginestra dei ghiaioni"},"1":{"name":"Portamento","value":"Cespuglio"},"2":{"name":"Altezza","value":"5-15 cm"},"3":{"name":"Tipo di vegetazione","value":"Ghiaioni (calc)"},"4":{"name":"Limite altitudinale inferiore","value":"400"},"5":{"name":"Limite altitudinale superiore","value":"1000"},"6":{"name":"Inizio fioritura","value":"Giugno"},"7":{"name":"Fine fioritura","value":"Luglio"},"8":{"name":"Autore","value":"(Fleischm.) Bald."},"9":{"name":"Forma biologica","value":"Ch suffr"},"10":{"name":"Codifica numerica","value":"3675045"},"11":{"name":"Progressivo","value":"1609"}},"region":{"0":{"id":"06","name":"Friuli-Venezia Giulia"}}}