{"id":"1085","taxa_kind_id":"16","name":"Genista radiata","description":"Arbusti nani caratterizzati dalle fg. opposte; anche i rami per lo pi\u00f9 appaiono opposti; i capolini sono portati da lunghi peduncoli nudi, legnosi e tenaci, ma assimilanti. Vivono generalm. in stazioni investite da correnti di aria umida dove {t1608} pu\u00f2 anche costituire estese formazioni.","creation_datetime":"2015-11-10 16:29:43","change_datetime":"2015-11-13 10:54:31","col_id":"","eol_id":null,"is_list":"0","taxa_kind_initials":"Gp.","taxa_kind_name":"Gruppo","status":"1","parent_taxa_id":"982","parent_taxa_name":"Genista","parent_taxa_initials":"Genere","dico":{"0":{"taxa_id":"1099","text":"Fi. inf. all'asc. di brattee indivise, ovate; vessillo pubescente sul dorso","name":"Genista radiata","taxa_kind_initials":"Sp.","taxa_kind_name":"Specie","status":"1"},"1":{"taxa_id":"1057","text":"Fi. tutti all'asc. di brattee divise in 3 segm. lineari; vessillo densam. pubescente su tutta la superficie","name":"Genista holopetala","taxa_kind_initials":"Sp.","taxa_kind_name":"Specie","status":"1"}},"image":{},"attribute":{},"region":{}}