{"id":"1237","taxa_kind_id":"15","name":"Vicia sativa subsp. angustifolia","description":"Calice con tubo di 4-5 mm e denti di 2-3 mm; corolla 14-16 mm; legume 3-4 X 30-40 mm, generalm. glabro.","creation_datetime":"2015-12-14 17:23:14","change_datetime":"2015-12-15 14:16:12","col_id":"","eol_id":"19864505","is_list":"0","taxa_kind_initials":"Sp.","taxa_kind_name":"Specie","status":"1","parent_taxa_id":"1235","parent_taxa_name":"Vicia sativa","parent_taxa_initials":"Specie","dico":{},"image":{},"attribute":{"0":{"name":"Tipo di vegetazione","value":"Prati aridi e brometi, in tutto il terr.: C."},"1":{"name":"Autore","value":"(Grufb.) Gaudin"}},"region":{}}