{"id":"1504","taxa_kind_id":"15","name":"Lotus commutatus","description":"Simile a {t1917}, ma densam. setoso-argentino; fg. con rachide lunga \u00bc-\u00bd dei segm. basali; calice 7.5-9 mm; legume spesso rigonfio in corrispondenza ai semi.<br \/><br \/>Steno-Medit.<br \/>Coste della Pen., verso N fino all'Abr. (Giulianova) ed al Laz. (Terracina), Sic: C, ma localizz.: segnalato anche in Lig. al C. Noli.<br \/><br \/><strong>Confus.<\/strong> - {t1917} e {t1918} sono di aspetto assai simile e spesso vennero confusi fra loro. Secondo la recente trattazione in Fl Europ. 2: 176 (1968) le due sp. si distinguono soprattutto per i rapporti di lunghezza fra rachide fogliare e segm. basali e per la lunghezza del calice. Heyn et Herrnstadt. KewBull.li: 299 (1967) propongono invece i caratteri della carena indicati anche nella nostra chiave analitica.","creation_datetime":"2016-02-28 09:01:08","change_datetime":"2016-02-28 09:20:07","col_id":"47ced434201ca018b34b06d960fe51ca","eol_id":"702890","is_list":"0","taxa_kind_initials":"Sp.","taxa_kind_name":"Specie","status":"1","parent_taxa_id":"1487","parent_taxa_name":"Lotus cytisoides","parent_taxa_initials":"Gruppo","dico":{},"image":{},"attribute":{"0":{"name":"Nome Italiano","value":"Ginestrino delle spiagge"},"1":{"name":"Portamento","value":"Cespuglio"},"2":{"name":"Altezza","value":"1-4 dm"},"3":{"name":"Tipo di vegetazione","value":"Dune mariti, raram. su ghiaie o scogli, (lit.)."},"4":{"name":"Inizio fioritura","value":"Marzo"},"5":{"name":"Fine fioritura","value":"Aprile"},"6":{"name":"Autore","value":"Guss."},"7":{"name":"Forma biologica","value":"Ch suffr"},"8":{"name":"Codifica numerica","value":"3698022"},"9":{"name":"Progressivo","value":"1918"},"10":{"name":"Sinonimi","value":"(L. creticus Auct. non L.)"}},"region":{"0":{"id":"07","name":"Liguria"},"1":{"id":"12","name":"Lazio"},"2":{"id":"13","name":"Abruzzo"},"3":{"id":"14","name":"Molise"},"4":{"id":"15","name":"Campania"},"5":{"id":"16","name":"Puglia"},"6":{"id":"17","name":"Basilicata"},"7":{"id":"18","name":"Calabria"},"8":{"id":"19","name":"Sicilia"},"9":{"id":"20","name":"Sardegna"}}}