{"id":"1540","taxa_kind_id":"15","name":"Anthyllis vulneraria subsp. baldensis","description":"Simile alla subsp. (o), della quale forse costituisce una variet\u00e0, ma corolla assai pi\u00f9 pallida, spesso venata di rossastro sul vessillo oppure con carena purpurea.<br \/><br \/>Fascia prealpina dal M. Baldo alle Grigne: C.<br \/><br \/><strong>Nota<\/strong> - Legata sia alla subsp. (o) che alla subsp. (n) da popolazioni difficilm. discriminabili; piante con il calice pi\u00f9 intensam arrossato alla fauce la collegano pure a (f).","creation_datetime":"2016-03-03 10:08:12","change_datetime":"2016-03-03 10:08:14","col_id":"","eol_id":"40489788","is_list":"0","taxa_kind_initials":"Sp.","taxa_kind_name":"Specie","status":"1","parent_taxa_id":"1525","parent_taxa_name":"Anthyllis vulneraria alpestris","parent_taxa_initials":"Gruppo","dico":{},"image":{"0":{"id":"935","taxa_id":"1540","filename":"\/00\/09\/35.png"}},"attribute":{"0":{"name":"Tipo di vegetazione","value":"Pascoli a Bromus erectus e Sesleria."},"1":{"name":"Limite altitudinale inferiore","value":"1000"},"2":{"name":"Limite altitudinale superiore","value":"2000"},"3":{"name":"Inizio fioritura","value":"Giugno"},"4":{"name":"Fine fioritura","value":"Luglio"},"5":{"name":"Autore","value":"(Kerner) Becker"},"6":{"name":"Sinonimi","value":"(= A. pallidi flora Jordan)"}},"region":{}}