{"0":{"id":"1329","name":"Ononis spinosa subsp. antiquorum","taxa_kind_initials":"Sp.","taxa_kind_name":"Specie"},"1":{"id":"1319","name":"Ononis natrix subsp.ramosissima","taxa_kind_initials":"Sp.","taxa_kind_name":"Specie"},"2":{"id":"1327","name":"Ononis spinosa subsp. foetens","taxa_kind_initials":"Sp.","taxa_kind_name":"Specie"},"3":{"id":"1318","name":"Ononis natrix subsp. natrix","taxa_kind_initials":"Sp.","taxa_kind_name":"Specie"},"4":{"id":"1328","name":"Ononis spinosa subsp. spinosa","taxa_kind_initials":"Sp.","taxa_kind_name":"Specie"},"5":{"id":"1320","name":"Ononis viscosa","taxa_kind_initials":"Sp.","taxa_kind_name":"Specie"},"6":{"id":"1325","name":"Ononis repens","taxa_kind_initials":"Sp.","taxa_kind_name":"Specie"},"7":{"id":"1304","name":"Ononis dentata","taxa_kind_initials":"Sp.","taxa_kind_name":"Specie"},"8":{"id":"1310","name":"Ononis hispida","taxa_kind_initials":"Sp.","taxa_kind_name":"Specie"},"9":{"id":"1296","name":"Ononis fruticosa","taxa_kind_initials":"Sp.","taxa_kind_name":"Specie"}}