{"0":{"id":"967","name":"Leguminosae V","taxa_kind_initials":"Gp.","taxa_kind_name":"Gruppo"},"1":{"id":"576","name":"Orchis sambucina","taxa_kind_initials":"Sp.","taxa_kind_name":"Specie"},"2":{"id":"575","name":"Orchis romana","taxa_kind_initials":"Sp.","taxa_kind_name":"Specie"},"3":{"id":"615","name":"Geum","taxa_kind_initials":"Gen.","taxa_kind_name":"Genere"},"4":{"id":"966","name":"Leguminosae II","taxa_kind_initials":"Gp.","taxa_kind_name":"Gruppo"},"5":{"id":"577","name":"Orchis insularis","taxa_kind_initials":"Sp.","taxa_kind_name":"Specie"},"6":{"id":"752","name":"Rosa moscata","taxa_kind_initials":"Sp.","taxa_kind_name":"Specie"},"7":{"id":"778","name":"Potentilla supina","taxa_kind_initials":"Sp.","taxa_kind_name":"Specie"},"8":{"id":"272","name":"Galeopsis bifida","taxa_kind_initials":"Sp.","taxa_kind_name":"Specie"},"9":{"id":"803","name":"Potentilla intermedia","taxa_kind_initials":"Sp.","taxa_kind_name":"Specie"}}