{"0":{"id":"877","name":"Alchemilla Calycinae","taxa_kind_initials":"Se.","taxa_kind_name":"Series"},"1":{"id":"879","name":"Alchemilla Vulgares subser. Glabrae","taxa_kind_initials":"Se.","taxa_kind_name":"Series"},"2":{"id":"874","name":"Alchemilla Vulgares subser. Heteropodae","taxa_kind_initials":"Se.","taxa_kind_name":"Series"},"3":{"id":"878","name":"Alchemilla schmidelyana","taxa_kind_initials":"Sp.","taxa_kind_name":"Specie"},"4":{"id":"873","name":"Alchemilla Pubescentes","taxa_kind_initials":"Se.","taxa_kind_name":"Series"},"5":{"id":"244","name":"Scutellaria rubiconda","taxa_kind_initials":"Sp.","taxa_kind_name":"Specie"},"6":{"id":"1234","name":"Vicia pimpinelloides","taxa_kind_initials":"Sp.","taxa_kind_name":"Specie"},"7":{"id":"289","name":"Leonurus","taxa_kind_initials":"Gen.","taxa_kind_name":"Genere"},"8":{"id":"243","name":"Scutellaria altissima","taxa_kind_initials":"Sp.","taxa_kind_name":"Specie"},"9":{"id":"255","name":"Sideritis hirsuta","taxa_kind_initials":"Sp.","taxa_kind_name":"Specie"}}