{"0":{"id":"220","name":"Teucrium spinosum","taxa_kind_initials":"Sp.","taxa_kind_name":"Specie"},"1":{"id":"312","name":"Stachys annua","taxa_kind_initials":"Sp.","taxa_kind_name":"Specie"},"2":{"id":"475","name":"Salvia pendula","taxa_kind_initials":"Sp.","taxa_kind_name":"Specie"},"3":{"id":"256","name":"Sideritis hyssopifolia","taxa_kind_initials":"Sp.","taxa_kind_name":"Specie"},"4":{"id":"973","name":"Hymenocarpus circinnatus","taxa_kind_initials":"Sp.","taxa_kind_name":"Specie"},"5":{"id":"950","name":"Prunus fruticosa","taxa_kind_initials":"Sp.","taxa_kind_name":"Specie"},"6":{"id":"401","name":"Thymus oenipontanus","taxa_kind_initials":"Sp.","taxa_kind_name":"Specie"},"7":{"id":"564","name":"Orchis italica","taxa_kind_initials":"Sp.","taxa_kind_name":"Specie"},"8":{"id":"1069","name":"Genista januensis","taxa_kind_initials":"Sp.","taxa_kind_name":"Specie"},"9":{"id":"1074","name":"Genista sericea","taxa_kind_initials":"Sp.","taxa_kind_name":"Specie"}}