{"0":{"id":"210","name":"Origanum","taxa_kind_initials":"Gen.","taxa_kind_name":"Genere"},"1":{"id":"619","name":"Agrimonia","taxa_kind_initials":"Gen.","taxa_kind_name":"Genere"},"2":{"id":"747","name":"Rosa micrantha","taxa_kind_initials":"Sp.","taxa_kind_name":"Specie"},"3":{"id":"294","name":"Ballota nigra","taxa_kind_initials":"Sp.","taxa_kind_name":"Specie"},"4":{"id":"339","name":"Glechoma sardoa","taxa_kind_initials":"Sp.","taxa_kind_name":"Specie"},"5":{"id":"319","name":"Stachys germanica","taxa_kind_initials":"Sp.","taxa_kind_name":"Specie"},"6":{"id":"739","name":"Rosa villosa","taxa_kind_initials":"Sp.","taxa_kind_name":"Specie"},"7":{"id":"662","name":"Glandulosi","taxa_kind_initials":"Gp.","taxa_kind_name":"Gruppo"},"8":{"id":"1021","name":"Oxytropis","taxa_kind_initials":"Gen.","taxa_kind_name":"Genere"},"9":{"id":"184","name":"Ziziphora capitata","taxa_kind_initials":"Sp.","taxa_kind_name":"Specie"}}