{"0":{"id":"1614","name":"CHIAVE PARZIALE C","taxa_kind_initials":"Gp.","taxa_kind_name":"Gruppo"},"1":{"id":"731","name":"Rubus incanescens","taxa_kind_initials":"Sp.","taxa_kind_name":"Specie"},"2":{"id":"736","name":"Rosa rubiginosa","taxa_kind_initials":"Sp.","taxa_kind_name":"Specie"},"3":{"id":"756","name":"Rosa glutinosa","taxa_kind_initials":"Sp.","taxa_kind_name":"Specie"},"4":{"id":"745","name":"Rosa serafinii","taxa_kind_initials":"Sp.","taxa_kind_name":"Specie"},"5":{"id":"1173","name":"Glycyrrhiza echinata","taxa_kind_initials":"Sp.","taxa_kind_name":"Specie"},"6":{"id":"270","name":"Galeopsis pubescens","taxa_kind_initials":"Sp.","taxa_kind_name":"Specie"},"7":{"id":"210","name":"Origanum","taxa_kind_initials":"Gen.","taxa_kind_name":"Genere"},"8":{"id":"737","name":"Rosa sicula","taxa_kind_initials":"Sp.","taxa_kind_name":"Specie"},"9":{"id":"740","name":"Rosa jundzillii","taxa_kind_initials":"Sp.","taxa_kind_name":"Specie"}}