{"0":{"id":"1004","name":"Ornithopus","taxa_kind_initials":"Gen.","taxa_kind_name":"Genere"},"1":{"id":"777","name":"Potentilla multifida","taxa_kind_initials":"Sp.","taxa_kind_name":"Specie"},"2":{"id":"1570","name":"Hedysarum spinosissimum","taxa_kind_initials":"Sp.","taxa_kind_name":"Specie"},"3":{"id":"1600","name":"Vulpia","taxa_kind_initials":"Gen.","taxa_kind_name":"Genere"},"4":{"id":"219","name":"Ajuga reptans","taxa_kind_initials":"Sp.","taxa_kind_name":"Specie"},"5":{"id":"1086","name":"Genista anglica","taxa_kind_initials":"Sp.","taxa_kind_name":"Specie"},"6":{"id":"1241","name":"Vicia sativa subsp. macrocarpa","taxa_kind_initials":"Sp.","taxa_kind_name":"Specie"},"7":{"id":"1234","name":"Vicia pimpinelloides","taxa_kind_initials":"Sp.","taxa_kind_name":"Specie"},"8":{"id":"598","name":"Epipactis purpurata","taxa_kind_initials":"Sp.","taxa_kind_name":"Specie"},"9":{"id":"1639","name":"CHIAVE PARZIALE D","taxa_kind_initials":"Gp.","taxa_kind_name":"Gruppo"}}