{"id":"518","taxa_kind_id":"15","name":"Corallorhiza trifida","description":"Rd. di aspetto coralloide, formata da tubercoli carnosi biancastri, diam. 2-3 mm, intricati e sviluppantisi in un piano; f. eretto avvolto dalle guaine almeno nella met\u00e0 inf., in alto un po' inverdito e clorofilliano. Fg. prive di clorofilla, ridotte alla sola guaina bruna, striate, con apice divergente. Racemo 3-9 fioro (talora anche 1 fi. singolo); fi. distanziati, arcuato-penduli su peduncoli di 2 mm: ovario 7 mm; brattee brune, triangolari (1 mm); tepali verde-giallastri, gli esterni 4-5-6 mm, gli interni un po' pi\u00f9 brevi; labello pi\u00f9 breve dei tepali oblungo, bianco con macchie porporine, presso la base portante 2 lobi lat. spesso indistinti; sperone mancante.","creation_datetime":"2015-05-12 11:55:13","change_datetime":"2015-08-03 11:02:46","col_id":"466f82fda00aca3a2a0a8e72e127deb0","eol_id":"1092012","is_list":"0","taxa_kind_initials":"Sp.","taxa_kind_name":"Specie","status":"1","parent_taxa_id":"490","parent_taxa_name":"Orchidaceae Gruppo V","parent_taxa_initials":"Gruppo","dico":{},"image":{"0":{"id":"326","taxa_id":"518","filename":"\/00\/03\/26.png"}},"attribute":{"0":{"name":"Altezza","value":"8-20 cm"},"1":{"name":"Nome Italiano","value":"Coralloriza"},"2":{"name":"Portamento","value":"Pianta perenne erbacea"},"3":{"name":"Tipo di vegetazione","value":"Boschi densi su terreno ricco di humus (soprattutto peccete, abetine e faggete)"},"4":{"name":"Limite altitudinale inferiore","value":"1200"},"5":{"name":"Limite altitudinale superiore","value":"1900"},"6":{"name":"Inizio fioritura","value":"Giugno"},"7":{"name":"Fine fioritura","value":"Luglio"},"8":{"name":"Autore","value":"Chatel"},"9":{"name":"Forma biologica","value":"G rhiz"},"10":{"name":"Codifica numerica","value":"1458001"}},"region":{"0":{"id":"01","name":"Piemonte"},"1":{"id":"02","name":"Valle d'Aosta\/Vall\u00e9e d'Aoste"},"2":{"id":"03","name":"Lombardia"},"3":{"id":"04","name":"Trentino-Alto Adige\/S\u00fcdtirol"},"4":{"id":"05","name":"Veneto"},"5":{"id":"06","name":"Friuli-Venezia Giulia"},"6":{"id":"07","name":"Liguria"},"7":{"id":"08","name":"Emilia Romagna"},"8":{"id":"09","name":"Toscana"},"9":{"id":"12","name":"Lazio"},"10":{"id":"13","name":"Abruzzo"},"11":{"id":"15","name":"Campania"}}}