{"id":"942","taxa_kind_id":"15","name":"Crataegus monogyna","description":"F. a corteccia compatta, grigio-aranciata; rami giovani scuri, glabri, con spine acute alla base dei rami abbreviati. Fg. con lamina chiara di sotto, a contorno ovale<br \/>0 rombico (2-4 X 2-4 cm) con 1-4 incisioni profonde per lato; lobi allungati, con bordi paralleli e senza dentelli almeno nella parte inf.; dentelli 2-4 presso l'apice; base tronca o cuneata ( \u00b1 a 90\u00b0); stipole a ventaglio. Corimbi multiflori con assi lanosi o pubescenti; petali bianchi, subrotondi (5-6 mm); stili 1; fr. a 1 seme.<br \/><br \/>1 Secondo Hegi la fioritura precede di 2 settimane quella di <em>Crataegus monogyna<\/em>.<br \/><br \/>Paleo-temp.<br \/>In tutto il terr.: C.<br \/><br \/><strong>Ibridi, confus. e variab.<\/strong> - La distinzione fra <em>Crataegus oxycanta<\/em> e <em>Crataegus monogyna<\/em> ha costituito da sempre un rompicapo per i fioristi. L'insieme dei caratteri differenziali da noi forniti \u00e8 valido solo per individui ben tipici, per\u00f2 nella maggioranza dei casi ci troviamo di fronte ad individui che, per l'uno o l'altro carattere, sono intermedi fra le due specie. Due soli caratteri hanno valore discriminante: la dentellatura dei lobi (continua in <em>Crataegus oxycanta<\/em>, limitata all'apice in <em>Crataegus monogyna<\/em>) ed il n. degli stili e semi nel fr. (2 in <em>Crataegus oxycanta<\/em>, 1 in <em>Crataegus monogyna<\/em>), per\u00f2 la correlazione fra i due non \u00e8 stretta, ed in popolazioni naturali non \u00e8 difficile trovare piante con fg. di <em>Crataegus oxycanta<\/em> e stili di <em>Crataegus monogyna<\/em> o viceversa. Le due specie possono vivere a pochi metri di distanza l'una dall'altra, per\u00f2 C. oxyacantha L. \u00e8 di preferenza in stazioni ombrose nei boschi chiusi, mentre <em>Crataegus monogyna<\/em> Jacq., ben pi\u00f9 xerofilo \u00e8 di regola ai margini del bosco ed in pieno sole. Per\u00f2 quando <em>Crataegus monogyna<\/em> vive nei boschi le fg. tendono ad avere lobi meno profondi, come in <em>Crataegus oxycanta<\/em>. Il numero cromosomico \u00e8 uguale per le due specie (2n = 34). L'ibrido fra le due ( X C. media Bechst.) \u00e8 frequente, e l'abbondanza di individui di difficile attribuzione fa pensare che in alcune zone sia diffuso quanto le specie allo stato puro.<br \/>Per i rapporti tra 1552 e <em>Crataegus monogyna<\/em> si cfr. l'ottimo studio di Lippert W., Ber. Bayer. Boi. Ges. 49: 165-198 (1978), del quale non si \u00e8 potuto tener conto, essendo questa Flora gi\u00e0 in stampa. <em>Crataegus monogyna<\/em> Jacq. \u00e8 specie assai variabile nella pubescenza (abbondante sulle fg. giovani, ma per lo pi\u00f9 scomparsa in estate). I rami dell'annata sono privi di fi. ed hanno fg. sparse con grandi (1-2 cm) stipole persistenti; i rami fioriferi portano le fg. riunite a 3-6 su rami laterali abbreviati (brachiblasti) e le stipole sono piccole, caduche, in estate generalm. scomparse; due rami differenti dello stesso individuo possono quindi dare l'impressione di specie del tutto diverse.<br \/><br \/><em>C. insegnae<\/em> (Tineo) Bertol. \u00e8 un ibrido fra <em>Crataegus monogyna<\/em> (b) e <em>Crataegus laciniata<\/em>, osservato in Sic; pure ibrido fra <em>Crataegus monogyna<\/em> e <em>Crataegus laciniata<\/em> \u00e8 <em>C. polvacantha<\/em> Jan.","creation_datetime":"2015-10-22 14:13:44","change_datetime":"2015-10-22 14:42:16","col_id":"a69c5fa0629a29945a3878a5c9600d22","eol_id":"628306","is_list":"0","taxa_kind_initials":"Sp.","taxa_kind_name":"Specie","status":"1","parent_taxa_id":"631","parent_taxa_name":"Crataegus","parent_taxa_initials":"Genere","dico":{"0":{"taxa_id":"945","text":"Getti giovani e fg. glabri o con pelosit\u00e0 scarsa. - Il tipo pi\u00f9 diffuso","name":"Crataegus monogyna subsp. monogyna","taxa_kind_initials":"Sp.","taxa_kind_name":"Specie","status":"0"},"1":{"taxa_id":"946","text":"Getti giovani e fg. densam. pubescenti; spinosit\u00e0 pi\u00f9 abbondante; lamine con 2-4 lobi profondi per lato. - Basil., Cal. e Sic, forse anche nel Lazio a Subiaco. (= C. azarella Griseb. ind. C. triloba Poiret)","name":"Crataegus monogyna subsp. azarella","taxa_kind_initials":"Sp.","taxa_kind_name":"Specie","status":"0"}},"image":{"0":{"id":"485","taxa_id":"942","filename":"\/00\/04\/85.png"},"1":{"id":"487","taxa_id":"942","filename":"\/00\/04\/87.png"}},"attribute":{"0":{"name":"Codifica numerica","value":"3345914"},"1":{"name":"Forma biologica","value":"P caesp"},"2":{"name":"Autore","value":"Jacq."},"3":{"name":"Fine fioritura","value":"Maggio"},"4":{"name":"Inizio fioritura","value":"Aprile"},"5":{"name":"Limite altitudinale superiore","value":"1500"},"6":{"name":"Limite altitudinale inferiore","value":"0"},"7":{"name":"Tipo di vegetazione","value":"Cespuglieti, siepi, boschi xerofdi degradati (pref. calc.)"},"8":{"name":"Altezza","value":"0.5-6 m"},"9":{"name":"Portamento","value":"Cespuglio"},"10":{"name":"Nome Italiano","value":"Biancospino comune; Azaruolo selvatico"},"11":{"name":"Progressivo","value":"1554"}},"region":{"0":{"id":"01","name":"Piemonte"},"1":{"id":"02","name":"Valle d'Aosta\/Vall\u00e9e d'Aoste"},"2":{"id":"03","name":"Lombardia"},"3":{"id":"04","name":"Trentino-Alto Adige\/S\u00fcdtirol"},"4":{"id":"05","name":"Veneto"},"5":{"id":"06","name":"Friuli-Venezia Giulia"},"6":{"id":"07","name":"Liguria"},"7":{"id":"08","name":"Emilia Romagna"},"8":{"id":"09","name":"Toscana"},"9":{"id":"10","name":"Umbria"},"10":{"id":"11","name":"Marche"},"11":{"id":"12","name":"Lazio"},"12":{"id":"13","name":"Abruzzo"},"13":{"id":"14","name":"Molise"},"14":{"id":"15","name":"Campania"},"15":{"id":"16","name":"Puglia"},"16":{"id":"17","name":"Basilicata"},"17":{"id":"18","name":"Calabria"},"18":{"id":"19","name":"Sicilia"},"19":{"id":"20","name":"Sardegna"}}}