{"0":{"id":"1194","name":"Vicia pseudocracca","taxa_kind_initials":"Sp.","taxa_kind_name":"Specie"},"1":{"id":"1498","name":"Lotus preslii","taxa_kind_initials":"Sp.","taxa_kind_name":"Specie"},"2":{"id":"1085","name":"Genista radiata","taxa_kind_initials":"Gp.","taxa_kind_name":"Gruppo"},"3":{"id":"1342","name":"Melilotus sulcata","taxa_kind_initials":"Sp.","taxa_kind_name":"Specie"},"4":{"id":"1574","name":"Onobrychis supina","taxa_kind_initials":"Sp.","taxa_kind_name":"Specie"},"5":{"id":"1496","name":"Lotus angustissimus","taxa_kind_initials":"Sp.","taxa_kind_name":"Specie"},"6":{"id":"1332","name":"Melilotus alba","taxa_kind_initials":"Sp.","taxa_kind_name":"Specie"},"7":{"id":"1786","name":"Festuca pratensis","taxa_kind_initials":"Sp.","taxa_kind_name":"Specie"},"8":{"id":"713","name":"Rubus pilocarpus","taxa_kind_initials":"Sp.","taxa_kind_name":"Specie"},"9":{"id":"1731","name":"Dactylis polygama","taxa_kind_initials":"Sp.","taxa_kind_name":"Specie"}}